realsense_helpers/__init__.py
realsense_helpers-0.0.0.dist-info/METADATA
realsense_helpers-0.0.0.dist-info/WHEEL
realsense_helpers-0.0.0.dist-info/licenses/LICENSE
realsense_helpers-0.0.0.dist-info/RECORD
